mytoolkit/__int__.py
mytoolkit/mjson.py
mytoolkit/alarms/slack.py
mytoolkit/basic/partition.py
mytoolkit/basic/strings.py
mytoolkit/db/dataclass.py
mytoolkit/db/mongo/base_model.py
mytoolkit/db/mongo/connection.py
mytoolkit-0.0.11.dist-info/LICENSE
mytoolkit-0.0.11.dist-info/METADATA
mytoolkit-0.0.11.dist-info/WHEEL
mytoolkit-0.0.11.dist-info/top_level.txt
mytoolkit-0.0.11.dist-info/RECORD
