Metadata-Version: 2.1
Name: mytoolkit
Version: 0.0.11
Summary: Some useful tools for python
Author-email: cn_qlg <cn_qlg@163.com>
License: MIT License        
Project-URL: Homepage, https://github.com/cn-qlg/mytoolkit
Project-URL: Bug Tracker, https://github.com/cn-qlg/mytoolkit/issues
Classifier: Programming Language :: Python :: 3
Classifier: License :: OSI Approved :: MIT License
Classifier: Operating System :: OS Independent
Requires-Python: >=3.7
License-File: LICENSE
Requires-Dist: pymongo (>=4.2.0)
